http2md/__init__.py
http2md/cli.py
http2md/crawler.py
http2md/crawler_async.py
http2md/crawler_site.py
http2md-0.9.dist-info/licenses/LICENSE
http2md-0.9.dist-info/METADATA
http2md-0.9.dist-info/WHEEL
http2md-0.9.dist-info/entry_points.txt
http2md-0.9.dist-info/top_level.txt
http2md-0.9.dist-info/RECORD
