Metadata-Version: 2.4
Name: http2md
Version: 0.9
Summary: A CLI tool to convert HTTP content to Markdown
Author-email: User <user@example.com>
Project-URL: Homepage, https://github.com/example/http2md
Project-URL: Bug Tracker, https://github.com/example/http2md/issues
Classifier: Programming Language :: Python :: 3
Classifier: License :: OSI Approved :: MIT License
Classifier: Operating System :: OS Independent
Requires-Python: >=3.11
License-File: LICENSE
Requires-Dist: playwright>=1.40.0
Requires-Dist: markdownify>=0.11.6
Requires-Dist: beautifulsoup4>=4.12.0
Requires-Dist: tqdm>=4.66.0
Dynamic: license-file
